HISTORY.rst
MANIFEST.in
README.rst
setup.py
wordpress_json/__init__.py
wordpress_json.egg-info/PKG-INFO
wordpress_json.egg-info/SOURCES.txt
wordpress_json.egg-info/dependency_links.txt
wordpress_json.egg-info/requires.txt
wordpress_json.egg-info/top_level.txt