Metadata-Version: 1.0
Name: wordpress-json
Version: 0.1.5
Summary: A thin wrapper for the Wordpress JSON API
Home-page: http://github.com/stylight/python-wordpress-json
Author: Raul Taranu, Dimitar Roustchev
Author-email: raul.taranu@stylight.com, dimitar.roustchev@stylight.com
License: MIT License
Keywords: wordpress json api
Platform: UNKNOWN
